{
  "active": false,
  "activeVersion": null,
  "activeVersionId": null,
  "connections": {
    "When clicking 'Execute workflow'": {
      "main": [
        [
          {
            "node": "評価管理取得",
            "type": "main",
            "index": 0
          },
          {
            "node": "グレードテーブル取得",
            "type": "main",
            "index": 0
          },
          {
            "node": "Get row(s) in sheet",
            "type": "main",
            "index": 0
          }
        ]
      ]
    },
    "Get row(s) in sheet": {
      "main": [
        [
          {
            "node": "Filter",
            "type": "main",
            "index": 0
          }
        ]
      ]
    },
    "評価管理取得": {
      "main": [
        [
          {
            "node": "Merge",
            "type": "main",
            "index": 0
          }
        ]
      ]
    },
    "Filter": {
      "main": [
        [
          {
            "node": "Merge",
            "type": "main",
            "index": 1
          }
        ]
      ]
    },
    "Merge": {
      "main": [
        [
          {
            "node": "Merge1",
            "type": "main",
            "index": 0
          }
        ]
      ]
    },
    "グレードテーブル取得": {
      "main": [
        [
          {
            "node": "Merge1",
            "type": "main",
            "index": 1
          }
        ]
      ]
    },
    "Merge1": {
      "main": [
        [
          {
            "node": "入力データ準備",
            "type": "main",
            "index": 0
          }
        ]
      ]
    },
    "入力データ準備": {
      "main": [
        [
          {
            "node": "サブワークフロー実行",
            "type": "main",
            "index": 0
          }
        ]
      ]
    }
  },
  "createdAt": "2026-03-05T10:15:47.411Z",
  "description": null,
  "id": "GQdaOFOyjuHfyTFbQ-3vE",
  "isArchived": false,
  "meta": {
    "templateCredsSetupCompleted": true
  },
  "name": "【新制度】目標設定",
  "nodes": [
    {
      "id": "bb432cc4-50b0-4239-bdae-1a777fae7481",
      "name": "When clicking 'Execute workflow'",
      "type": "n8n-nodes-base.manualTrigger",
      "typeVersion": 1,
      "position": [
        -416,
        32
      ],
      "parameters": {}
    },
    {
      "id": "6296486e-f801-4248-9c44-67eb095b5374",
      "name": "評価管理取得",
      "type": "n8n-nodes-base.googleSheets",
      "typeVersion": 4.7,
      "position": [
        16,
        -208
      ],
      "parameters": {
        "documentId": {
          "__rl": true,
          "value": "124JGHYceu0NeAS_tvV9EiuaMLUU0bAcYjIynwNXcnm0",
          "mode": "list",
          "cachedResultName": "目標・評価管理シート",
          "cachedResultUrl": "https://docs.google.com/spreadsheets/d/124JGHYceu0NeAS_tvV9EiuaMLUU0bAcYjIynwNXcnm0/edit?usp=drivesdk"
        },
        "sheetName": {
          "__rl": true,
          "value": 404530097,
          "mode": "list",
          "cachedResultName": "評価管理",
          "cachedResultUrl": "https://docs.google.com/spreadsheets/d/124JGHYceu0NeAS_tvV9EiuaMLUU0bAcYjIynwNXcnm0/edit#gid=404530097"
        },
        "options": {}
      },
      "credentials": {
        "googleSheetsOAuth2Api": {
          "id": "ZfwIn54p5eaFX5s0",
          "name": "Google Sheets account 2"
        }
      }
    },
    {
      "id": "48b6af51-eede-4cee-86f8-afd00eaf5a80",
      "name": "Get row(s) in sheet",
      "type": "n8n-nodes-base.googleSheets",
      "typeVersion": 4.7,
      "position": [
        -208,
        32
      ],
      "parameters": {
        "documentId": {
          "__rl": true,
          "value": "1OBqgWZDLYIFhrnCx37ixJorcAGuNSiwDV3wSMzPyP3I",
          "mode": "list",
          "cachedResultName": "社員基本情報",
          "cachedResultUrl": "https://docs.google.com/spreadsheets/d/1OBqgWZDLYIFhrnCx37ixJorcAGuNSiwDV3wSMzPyP3I/edit?usp=drivesdk"
        },
        "sheetName": {
          "__rl": true,
          "value": "gid=0",
          "mode": "list",
          "cachedResultName": "シート1",
          "cachedResultUrl": "https://docs.google.com/spreadsheets/d/1OBqgWZDLYIFhrnCx37ixJorcAGuNSiwDV3wSMzPyP3I/edit#gid=0"
        },
        "options": {}
      },
      "credentials": {
        "googleSheetsOAuth2Api": {
          "id": "ZfwIn54p5eaFX5s0",
          "name": "Google Sheets account 2"
        }
      }
    },
    {
      "id": "42b24cf4-3a74-4e5d-b1ec-daf4f89ade3e",
      "name": "グレードテーブル取得",
      "type": "n8n-nodes-base.googleSheets",
      "typeVersion": 4.7,
      "position": [
        16,
        304
      ],
      "parameters": {
        "documentId": {
          "__rl": true,
          "value": "168L2-CivFCuVbyQd4CNgHX_sD7SLr2rUC9AsmcnBT1I",
          "mode": "list",
          "cachedResultName": "[提案] YOKU人事制度",
          "cachedResultUrl": "https://docs.google.com/spreadsheets/d/168L2-CivFCuVbyQd4CNgHX_sD7SLr2rUC9AsmcnBT1I/edit?usp=drivesdk"
        },
        "sheetName": {
          "__rl": true,
          "value": 198206375,
          "mode": "list",
          "cachedResultName": "グレードテーブル_ver1.1",
          "cachedResultUrl": "https://docs.google.com/spreadsheets/d/168L2-CivFCuVbyQd4CNgHX_sD7SLr2rUC9AsmcnBT1I/edit#gid=198206375"
        },
        "options": {}
      },
      "credentials": {
        "googleSheetsOAuth2Api": {
          "id": "ZfwIn54p5eaFX5s0",
          "name": "Google Sheets account 2"
        }
      }
    },
    {
      "id": "e049e385-5332-41d7-88af-6d29a138383d",
      "name": "Filter",
      "type": "n8n-nodes-base.filter",
      "typeVersion": 2.3,
      "position": [
        16,
        64
      ],
      "parameters": {
        "conditions": {
          "options": {
            "caseSensitive": true,
            "leftValue": "",
            "typeValidation": "strict",
            "version": 3
          },
          "conditions": [
            {
              "id": "7d36f3ce-493d-46db-a616-284704c239dd",
              "leftValue": "={{ $json['社員番号'] }}",
              "rightValue": "A018",
              "operator": {
                "type": "string",
                "operation": "equals"
              }
            }
          ],
          "combinator": "and"
        },
        "options": {}
      }
    },
    {
      "id": "merge-sync-a",
      "name": "Merge",
      "type": "n8n-nodes-base.merge",
      "typeVersion": 3.2,
      "position": [
        272,
        -64
      ],
      "parameters": {
        "mode": "append"
      }
    },
    {
      "id": "merge-sync-b",
      "name": "Merge1",
      "type": "n8n-nodes-base.merge",
      "typeVersion": 3.2,
      "position": [
        500,
        100
      ],
      "parameters": {
        "mode": "append"
      }
    },
    {
      "id": "code-prep",
      "name": "入力データ準備",
      "type": "n8n-nodes-base.code",
      "typeVersion": 2,
      "position": [
        720,
        100
      ],
      "parameters": {
        "jsCode": "// 評価管理から対象社員のデータをフィルタリング\nconst allEvaluation = $('評価管理取得').all();\nconst employees = $('Filter').all();\nconst gradeTable = $('グレードテーブル取得').all().map(r => r.json);\n\nconst results = [];\nfor (const emp of employees) {\n  const empNo = emp.json['社員番号'];\n  const hrFolderId = emp.json['人事フォルダID'];\n\n  // この社員の評価データをフィルタ\n  const evalData = allEvaluation\n    .filter(r => r.json['社員番号'] === empNo)\n    .map(r => r.json);\n\n  results.push({\n    json: {\n      evaluationData: evalData,\n      gradeTable: gradeTable,\n      hrFolderId: hrFolderId\n    }\n  });\n}\n\nreturn results;"
      }
    },
    {
      "id": "exec-sub",
      "name": "サブワークフロー実行",
      "type": "n8n-nodes-base.executeWorkflow",
      "typeVersion": 1.2,
      "position": [
        940,
        100
      ],
      "parameters": {
        "workflowId": {
          "__rl": true,
          "value": "Etheyfa0EdEr8Si0",
          "mode": "id"
        }
      }
    }
  ],
  "pinData": {},
  "settings": {
    "executionOrder": "v1",
    "availableInMCP": false,
    "callerPolicy": "workflowsFromSameOwner"
  },
  "shared": [
    {
      "updatedAt": "2026-03-06T05:24:31.390Z",
      "createdAt": "2026-03-06T05:24:31.390Z",
      "role": "workflow:owner",
      "workflowId": "GQdaOFOyjuHfyTFbQ-3vE",
      "projectId": "mwID5OTVq3DrYryq",
      "project": {
        "updatedAt": "2025-11-13T14:51:48.267Z",
        "createdAt": "2025-11-13T14:36:59.116Z",
        "id": "mwID5OTVq3DrYryq",
        "name": "Jumpei Tamura <gtamu.dip@gmail.com>",
        "type": "personal",
        "icon": null,
        "description": null,
        "creatorId": "36fefead-da4e-48c0-99da-60cc0ed98b20",
        "projectRelations": [
          {
            "updatedAt": "2025-11-13T14:36:59.117Z",
            "createdAt": "2025-11-13T14:36:59.117Z",
            "userId": "36fefead-da4e-48c0-99da-60cc0ed98b20",
            "projectId": "mwID5OTVq3DrYryq",
            "user": {
              "updatedAt": "2026-03-10T02:13:08.000Z",
              "createdAt": "2025-11-13T14:36:48.586Z",
              "id": "36fefead-da4e-48c0-99da-60cc0ed98b20",
              "email": "gtamu.dip@gmail.com",
              "firstName": "Jumpei",
              "lastName": "Tamura",
              "personalizationAnswers": {
                "version": "v4",
                "personalization_survey_submitted_at": "2025-11-13T14:51:58.989Z",
                "personalization_survey_n8n_version": "1.98.1"
              },
              "settings": {
                "userActivated": true,
                "easyAIWorkflowOnboarded": true,
                "firstSuccessfulWorkflowId": "nJ6NxHK18rgZXMP4",
                "userActivatedAt": 1763558344486,
                "npsSurvey": {
                  "waitingForResponse": true,
                  "ignoredCount": 1,
                  "lastShownAt": 1772775475677
                }
              },
              "disabled": false,
              "mfaEnabled": false,
              "lastActiveAt": "2026-03-10",
              "isPending": false
            }
          }
        ]
      }
    }
  ],
  "staticData": null,
  "tags": [],
  "triggerCount": 0,
  "updatedAt": "2026-03-10T02:50:51.639Z",
  "versionCounter": 17,
  "versionId": "6555796e-e66a-47e8-9b45-c5b52cd6861b"
}